arxivfeedagent/__init__.py
arxivfeedagent/checker.py
arxivfeedagent/cli.py
arxivfeedagent/feedloader.py
arxivfeedagent/library.py
arxivfeedagent/main.py
arxivfeedagent/paper.py
arxivfeedagent/summarizer.py
arxivfeedagent-0.1.0.dist-info/METADATA
arxivfeedagent-0.1.0.dist-info/WHEEL
arxivfeedagent-0.1.0.dist-info/entry_points.txt
arxivfeedagent-0.1.0.dist-info/top_level.txt
arxivfeedagent-0.1.0.dist-info/RECORD
