Metadata-Version: 2.4
Name: arxivfeedagent
Version: 0.1.0
Summary: Add your description here
Requires-Python: >=3.14
Requires-Dist: click>=8.3.0
Requires-Dist: feedparser>=6.0.12
Requires-Dist: openai>=2.2.0
Requires-Dist: pydantic>=2.12.0
Requires-Dist: reader>=3.19
Requires-Dist: sienna>=0.2.6
